{
	"apidwn" : [
		{
			"id": "12d8e618-c164-4083-801f-3b855dc5fbb8",
			"filename": "A2111_FR/REPAIR_TUTO/resources/step4.jpg",
			"label": null,
			"lastModified": "2020-08-18T11:21:49.538Z",
			"contentId": "REPAIR_TUTO",
			"language": "fr",
			"designation": "iPhone 11",
			"maintenanceLevel": "ILM",
			"partNumbers": [
				"A2111"
			],
			"resourceCategory": "REPAIR"
		},
		{
			"id": "14ca2b7a-b356-4f6f-ab0d-4e4c7a2c4342",
			"filename": "A2111_FR/REPAIR_TUTO/resources/step3.jpg",
			"label": null,
			"lastModified": "2020-08-18T11:21:49.444Z",
			"contentId": "REPAIR_TUTO",
			"language": "fr",
			"designation": "iPhone 11",
			"maintenanceLevel": "ILM",
			"partNumbers": [
				"A2111"
			],
			"resourceCategory": "REPAIR"
		},
		{
			"id": "18dc750e-1d73-4e13-b45e-9cc2ec16527b",
			"filename": "S7/fr/ILM/G930V/REPAIR_TUTO/resources/step13.png",
			"label": "step13.png",
			"lastModified": "2020-10-13T11:46:24.964Z",
			"contentId": "DIAG_EQ_TREE",
			"language": "fr",
			"designation": "S7",
			"maintenanceLevel": "ILM",
			"partNumbers": [
				"G930F",
				"G930V"
			],
			"resourceCategory": "TROUBLESHOOTING"
		},
		{
			"id": "19ad42fb-d1cc-4a6c-9b1e-4bf5ff3fe3a7",
			"filename": "S7/fr/ILM/G930V/REPAIR_TUTO/resources/Step1.png",
			"label": "Step1.png",
			"lastModified": "2020-10-13T11:46:24.654Z",
			"contentId": "DIAG_EQ_TREE",
			"language": "fr",
			"designation": "S7",
			"maintenanceLevel": "ILM",
			"partNumbers": [
				"G930F",
				"G930V"
			],
			"resourceCategory": "TROUBLESHOOTING"
		},
		{
			"id": "1d571994-51e2-4799-ba87-093b1b0da82e",
			"filename": "A2111_FR/DIAG_EQ_TREE/resources/debrancher-chargeur-pas-utilisé (1).jpg",
			"label": null,
			"lastModified": "2020-08-18T11:21:49.254Z",
			"contentId": "DIAG_EQ_TREE",
			"language": "fr",
			"designation": "iPhone 11",
			"maintenanceLevel": "ILM",
			"partNumbers": [
				"A2111"
			],
			"resourceCategory": "TROUBLESHOOTING"
		},
		{
			"id": "2130d4d7-ad4c-489a-b9b2-52fdb0af614d",
			"filename": "S7/fr/ILM/G930F/REPAIR_TUTO/resources/step8-2.png",
			"label": "step8-2.png",
			"lastModified": "2020-10-13T11:46:24.351Z",
			"contentId": "DIAG_EQ_TREE",
			"language": "fr",
			"designation": "S7",
			"maintenanceLevel": "ILM",
			"partNumbers": [
				"G930F",
				"G930V"
			],
			"resourceCategory": "TROUBLESHOOTING"
		},
		{
			"id": "24e73c7e-782e-422f-a445-b004936fd10c",
			"filename": "IF3290741_NA/EQ_IMAGE_REF/IF3290741.PNG",
			"label": null,
			"lastModified": "2020-08-05T07:42:20.351Z",
			"contentId": "EQ_IMAGE_REF",
			"language": "NA",
			"designation": "GALAXY S7 CHARGING DAUGHTER BOARD (GLOBAL)",
			"maintenanceLevel": "NA",
			"partNumbers": [
				"IF3290741"
			],
			"resourceCategory": "IMAGE"
		},
		{
			"id": "2828b06f-4331-40de-99dc-b4036f453a7a",
			"filename": "S7/fr/ILM/G930F/REPAIR_TUTO/resources/step2.png",
			"label": "step2.png",
			"lastModified": "2020-10-13T11:46:24.153Z",
			"contentId": "DIAG_EQ_TREE",
			"language": "fr",
			"designation": "S7",
			"maintenanceLevel": "ILM",
			"partNumbers": [
				"G930F",
				"G930V"
			],
			"resourceCategory": "TROUBLESHOOTING"
		},
		{
			"id": "31407a50-5bee-47a9-8120-d3fa2dd8b4a1",
			"filename": "0123456789_FR/DOC_MAE/REPAIR_TUTO/resources/blanc.png",
			"label": null,
			"lastModified": "2020-06-24T11:41:00.350Z",
			"contentId": "DOC_MAE",
			"language": "fr",
			"designation": "TEST",
			"maintenanceLevel": "OLM",
			"partNumbers": [
				"0123456789"
			],
			"resourceCategory": "DOC"
		},
		{
			"id": "34fd8491-41ae-4253-bef1-f6181b68a70a",
			"filename": "A1984_EN/DOC_MEO/iPhone_XR_PER_sept2018.pdf",
			"label": null,
			"lastModified": "2020-08-19T11:55:43.514Z",
			"contentId": "DOC_MEO",
			"language": "en",
			"designation": "iPhone XR",
			"maintenanceLevel": "ILM",
			"partNumbers": [
				"A1984"
			],
			"resourceCategory": "DOC"
		},
		{
			"id": "3583b188-cf47-4c3c-817b-e5ced875629d",
			"filename": "S7/fr/ILM/G930F/REPAIR_TUTO/resources/Step1.png",
			"label": "Step1.png",
			"lastModified": "2020-10-13T11:46:24.117Z",
			"contentId": "DIAG_EQ_TREE",
			"language": "fr",
			"designation": "S7",
			"maintenanceLevel": "ILM",
			"partNumbers": [
				"G930F",
				"G930V"
			],
			"resourceCategory": "TROUBLESHOOTING"
		},
		{
			"id": "39175531-6cc7-4bb1-849d-77ff78c9e884",
			"filename": "S7/fr/ILM/G930V/DIAG_EQ_TREE/troubleshooting-6378aff5-5d8d-41f8-a4b9-f781e5edf233.json",
			"label": "Samsung Galaxy S7 - Batterie",
			"lastModified": "2020-10-13T11:46:24.605Z",
			"contentId": "DIAG_EQ_TREE",
			"language": "fr",
			"designation": "S7",
			"maintenanceLevel": "ILM",
			"partNumbers": [
				"G930F",
				"G930V"
			],
			"resourceCategory": "TROUBLESHOOTING"
		},
		{
			"id": "3ac9d0df-d0d4-415a-a844-e41e323ef350",
			"filename": "S7/fr/ILM/G930V/REPAIR_TUTO/resources/step10.png",
			"label": "step10.png",
			"lastModified": "2020-10-13T11:46:24.890Z",
			"contentId": "DIAG_EQ_TREE",
			"language": "fr",
			"designation": "S7",
			"maintenanceLevel": "ILM",
			"partNumbers": [
				"G930F",
				"G930V"
			],
			"resourceCategory": "TROUBLESHOOTING"
		},
		{
			"id": "3d1de7af-f142-4b60-89c0-a65db9cee7a0",
			"filename": "S7/fr/ILM/G930F/REPAIR_TUTO/resources/step13.png",
			"label": "step13.png",
			"lastModified": "2020-10-13T11:46:24.503Z",
			"contentId": "DIAG_EQ_TREE",
			"language": "fr",
			"designation": "S7",
			"maintenanceLevel": "ILM",
			"partNumbers": [
				"G930F",
				"G930V"
			],
			"resourceCategory": "TROUBLESHOOTING"
		},
		{
			"id": "43ab0456-db17-4514-932b-ea4b2e31fe35",
			"filename": "S8/fr/ILM/G950F/REPAIR_TUTO/resources/step3.png",
			"label": "step3.png",
			"lastModified": "2020-10-13T11:34:48.833Z",
			"contentId": "DIAG_EQ_TREE",
			"language": "fr",
			"designation": "S8",
			"maintenanceLevel": "ILM",
			"partNumbers": [
				"G950F"
			],
			"resourceCategory": "TROUBLESHOOTING"
		},
		{
			"id": "4cb8f1e7-8a2a-483a-b707-67ece46d3a7c",
			"filename": "S7/fr/ILM/G930V/REPAIR_TUTO/resources/step6.png",
			"label": "step6.png",
			"lastModified": "2020-10-13T11:46:24.761Z",
			"contentId": "DIAG_EQ_TREE",
			"language": "fr",
			"designation": "S7",
			"maintenanceLevel": "ILM",
			"partNumbers": [
				"G930F",
				"G930V"
			],
			"resourceCategory": "TROUBLESHOOTING"
		},
		{
			"id": "4dd0a117-e6f1-49de-b4ef-7995957de0bb",
			"filename": "IF3290291_NA/EQ_IMAGE_REF/IF3290291.PNG",
			"label": null,
			"lastModified": "2020-08-05T07:41:40.242Z",
			"contentId": "EQ_IMAGE_REF",
			"language": "NA",
			"designation": "GALAXY S7 REAR CAMERA",
			"maintenanceLevel": "NA",
			"partNumbers": [
				"IF3290291"
			],
			"resourceCategory": "IMAGE"
		},
		{
			"id": "4fe4431b-3bff-4d50-abc6-5b4a18f27a34",
			"filename": "S7/fr/ILM/G930V/REPAIR_TUTO/repair_summary.json",
			"label": "",
			"lastModified": "2020-10-13T11:46:25.046Z",
			"contentId": "REPAIR_TUTO",
			"language": "fr",
			"designation": "S7",
			"maintenanceLevel": "ILM",
			"partNumbers": [
				"G930F",
				"G930V"
			],
			"resourceCategory": "REPAIR"
		},
		{
			"id": "53c94350-d6ab-42ff-9606-922c2d71e1f9",
			"filename": "A2111_FR/EQ_IMAGE_REF/Apple-iPhone-11-64-Go-6-1-Mauve.jpg",
			"label": null,
			"lastModified": "2020-08-18T11:21:49.699Z",
			"contentId": "EQ_IMAGE_REF",
			"language": "fr",
			"designation": "iPhone 11",
			"maintenanceLevel": "ILM",
			"partNumbers": [
				"A2111"
			],
			"resourceCategory": "IMAGE"
		},
		{
			"id": "57135fef-9a57-44e2-a4f6-20141b4141a0",
			"filename": "A2111_FR/REPAIR_TUTO/resources/step2.jpg",
			"label": null,
			"lastModified": "2020-08-18T11:21:49.407Z",
			"contentId": "REPAIR_TUTO",
			"language": "fr",
			"designation": "iPhone 11",
			"maintenanceLevel": "ILM",
			"partNumbers": [
				"A2111"
			],
			"resourceCategory": "REPAIR"
		},
		{
			"id": "57cc0dbd-a8a5-41e5-907e-e7e21a2c8e53",
			"filename": "S7/fr/ILM/G930F/REPAIR_TUTO/replace_battery_s7.json",
			"label": "replace_battery_s7.json",
			"lastModified": "2020-10-13T11:46:24.566Z",
			"contentId": "REPAIR_TUTO",
			"language": "fr",
			"designation": "S7",
			"maintenanceLevel": "ILM",
			"partNumbers": [
				"G930F",
				"G930V"
			],
			"resourceCategory": "REPAIR"
		},
		{
			"id": "5ad47929-744f-41c1-ab62-9bf23edc3013",
			"filename": "S7/fr/ILM/G930V/REPAIR_TUTO/resources/step14-1.png",
			"label": "step14-1.png",
			"lastModified": "2020-10-13T11:46:24.986Z",
			"contentId": "DIAG_EQ_TREE",
			"language": "fr",
			"designation": "S7",
			"maintenanceLevel": "ILM",
			"partNumbers": [
				"G930F",
				"G930V"
			],
			"resourceCategory": "TROUBLESHOOTING"
		},
		{
			"id": "5d4d1f38-6b50-4d7c-af95-fddddea5e181",
			"filename": "0123456789_FR/DOC_MAE/DIAG_EQ_TREE/resources/Error_Code1.png",
			"label": null,
			"lastModified": "2020-06-24T11:41:00.349Z",
			"contentId": "DOC_MAE",
			"language": "fr",
			"designation": "TEST",
			"maintenanceLevel": "OLM",
			"partNumbers": [
				"0123456789"
			],
			"resourceCategory": "DOC"
		},
		{
			"id": "63229fd9-1988-4525-a6db-35d02e3413a4",
			"filename": "IF3290051_NA/EQ_IMAGE_REF/IF3290051.PNG",
			"label": null,
			"lastModified": "2020-08-05T07:43:18.264Z",
			"contentId": "EQ_IMAGE_REF",
			"language": "NA",
			"designation": "GALAXY S7/S7 EDGE FRONT CAMERA",
			"maintenanceLevel": "NA",
			"partNumbers": [
				"IF3290051"
			],
			"resourceCategory": "IMAGE"
		},
		{
			"id": "674edd20-da03-4da7-98c3-625920b10212",
			"filename": "A2111_FR/REPAIR_TUTO/restartingyouriphone11.json",
			"label": null,
			"lastModified": "2020-08-18T11:21:49.565Z",
			"contentId": "REPAIR_TUTO",
			"language": "fr",
			"designation": "iPhone 11",
			"maintenanceLevel": "ILM",
			"partNumbers": [
				"A2111"
			],
			"resourceCategory": "REPAIR"
		},
		{
			"id": "68ef54bf-90d8-47de-9792-2b5bb40bb932",
			"filename": "S7/fr/ILM/G930V/REPAIR_TUTO/resources/step8-1.png",
			"label": "step8-1.png",
			"lastModified": "2020-10-13T11:46:24.812Z",
			"contentId": "DIAG_EQ_TREE",
			"language": "fr",
			"designation": "S7",
			"maintenanceLevel": "ILM",
			"partNumbers": [
				"G930F",
				"G930V"
			],
			"resourceCategory": "TROUBLESHOOTING"
		},
		{
			"id": "69cb6f15-cc97-4986-a667-2f7c937075af",
			"filename": "S7/fr/ILM/G930V/REPAIR_TUTO/resources/step8-2.png",
			"label": "step8-2.png",
			"lastModified": "2020-10-13T11:46:24.830Z",
			"contentId": "DIAG_EQ_TREE",
			"language": "fr",
			"designation": "S7",
			"maintenanceLevel": "ILM",
			"partNumbers": [
				"G930F",
				"G930V"
			],
			"resourceCategory": "TROUBLESHOOTING"
		},
		{
			"id": "6a82eedd-5232-48b5-ae29-7570bf4d6eed",
			"filename": "0123456789_FR/DOC_MAE/DIAG_EQ_TREE/resources/ENTR.png",
			"label": null,
			"lastModified": "2020-06-24T11:41:00.348Z",
			"contentId": "DOC_MAE",
			"language": "fr",
			"designation": "TEST",
			"maintenanceLevel": "OLM",
			"partNumbers": [
				"0123456789"
			],
			"resourceCategory": "DOC"
		},
		{
			"id": "6c70bbfd-3bbd-4117-b2e4-102a837faae5",
			"filename": "S7/fr/ILM/G930F/REPAIR_TUTO/resources/step14-1.png",
			"label": "step14-1.png",
			"lastModified": "2020-10-13T11:46:24.527Z",
			"contentId": "DIAG_EQ_TREE",
			"language": "fr",
			"designation": "S7",
			"maintenanceLevel": "ILM",
			"partNumbers": [
				"G930F",
				"G930V"
			],
			"resourceCategory": "TROUBLESHOOTING"
		},
		{
			"id": "6eb231cc-1925-4965-9680-413b26abc8c9",
			"filename": "0123456789_FR/DOC_MAE/0123456789_FR-test.zip",
			"label": null,
			"lastModified": "2020-06-24T11:40:33.805Z",
			"contentId": "DOC_MAE",
			"language": "fr",
			"designation": "TEST",
			"maintenanceLevel": "OLM",
			"partNumbers": [
				"0123456789"
			],
			"resourceCategory": "DOC"
		},
		{
			"id": "6f2709d7-840b-4540-9fb9-47a62632acef",
			"filename": "S7/fr/ILM/G930V/REPAIR_TUTO/resources/step3.png",
			"label": "step3.png",
			"lastModified": "2020-10-13T11:46:24.700Z",
			"contentId": "DIAG_EQ_TREE",
			"language": "fr",
			"designation": "S7",
			"maintenanceLevel": "ILM",
			"partNumbers": [
				"G930F",
				"G930V"
			],
			"resourceCategory": "TROUBLESHOOTING"
		},
		{
			"id": "7118212b-4eaa-40cf-b33b-84eb88580e82",
			"filename": "S7/fr/ILM/G930F/REPAIR_TUTO/resources/step5.png",
			"label": "step5.png",
			"lastModified": "2020-10-13T11:46:24.248Z",
			"contentId": "DIAG_EQ_TREE",
			"language": "fr",
			"designation": "S7",
			"maintenanceLevel": "ILM",
			"partNumbers": [
				"G930F",
				"G930V"
			],
			"resourceCategory": "TROUBLESHOOTING"
		},
		{
			"id": "72d8f3ab-8e32-4886-868d-3aae93fd9a33",
			"filename": "A2111_FR/DIAG_EQ_TREE/troubleshooting-5f353c546436850018a8618c.json",
			"label": "iPhone 11 - Will not power up",
			"lastModified": "2020-08-18T11:21:49.174Z",
			"contentId": "DIAG_EQ_TREE",
			"language": "fr",
			"designation": "iPhone 11",
			"maintenanceLevel": "ILM",
			"partNumbers": [
				"A2111"
			],
			"resourceCategory": "TROUBLESHOOTING"
		},
		{
			"id": "7b01e280-6e08-48b7-9f60-afd3f736438e",
			"filename": "0123456789_FR/DOC_MTMI/TRC9210_MTMI_63994136-194_FR_Générique_2018_10.pdf",
			"label": null,
			"lastModified": "2020-06-24T13:17:19.159Z",
			"contentId": "DOC_MTMI",
			"language": "fr",
			"designation": "TEST",
			"maintenanceLevel": "OLM",
			"partNumbers": [
				"0123456789"
			],
			"resourceCategory": "DOC"
		},
		{
			"id": "7b4d5e7b-e572-4499-b525-84d7b7dfca82",
			"filename": "S8/fr/ILM/G950F/DIAG_EQ_TREE/troubleshooting-1c59d6e4-f880-4c00-a768-17f521543f21.json",
			"label": "Samsung Galaxy S8 - Test",
			"lastModified": "2020-10-13T11:34:48.712Z",
			"contentId": "DIAG_EQ_TREE",
			"language": "fr",
			"designation": "S8",
			"maintenanceLevel": "ILM",
			"partNumbers": [
				"G950F"
			],
			"resourceCategory": "TROUBLESHOOTING"
		},
		{
			"id": "7eb529d4-49f0-47e9-b798-23a49800be4f",
			"filename": "A2111_FR/REPAIR_TUTO/repair_summary.json",
			"label": null,
			"lastModified": "2020-08-18T11:21:49.705Z",
			"contentId": "REPAIR_TUTO",
			"language": "fr",
			"designation": "iPhone 11",
			"maintenanceLevel": "ILM",
			"partNumbers": [
				"A2111"
			],
			"resourceCategory": "REPAIR"
		},
		{
			"id": "7fd74f4a-b2a0-4e0e-98ad-0b4ecc235af8",
			"filename": "S7/fr/ILM/G930V/REPAIR_TUTO/replace_battery_s7.json",
			"label": "replace_battery_s7.json",
			"lastModified": "2020-10-13T11:46:25.027Z",
			"contentId": "REPAIR_TUTO",
			"language": "fr",
			"designation": "S7",
			"maintenanceLevel": "ILM",
			"partNumbers": [
				"G930F",
				"G930V"
			],
			"resourceCategory": "REPAIR"
		},
		{
			"id": "8ac09a42-9782-46ef-beed-739502e8fcc2",
			"filename": "S7/fr/ILM/G930V/REPAIR_TUTO/resources/step5.png",
			"label": "step5.png",
			"lastModified": "2020-10-13T11:46:24.739Z",
			"contentId": "DIAG_EQ_TREE",
			"language": "fr",
			"designation": "S7",
			"maintenanceLevel": "ILM",
			"partNumbers": [
				"G930F",
				"G930V"
			],
			"resourceCategory": "TROUBLESHOOTING"
		},
		{
			"id": "8c90d1ba-5d0d-4294-aa40-900df6d35d4a",
			"filename": "A2111_FR/DOC_MTMI/iphone-11-128gb-mauve.pdf",
			"label": null,
			"lastModified": "2020-08-18T11:21:49.642Z",
			"contentId": "DOC_MTMI",
			"language": "fr",
			"designation": "iPhone 11",
			"maintenanceLevel": "ILM",
			"partNumbers": [
				"A2111"
			],
			"resourceCategory": "DOC"
		},
		{
			"id": "8edc5f61-1706-43ad-9ba3-de7055dd2f45",
			"filename": "S7/fr/ILM/G930F/REPAIR_TUTO/resources/step9.png",
			"label": "step9.png",
			"lastModified": "2020-10-13T11:46:24.392Z",
			"contentId": "DIAG_EQ_TREE",
			"language": "fr",
			"designation": "S7",
			"maintenanceLevel": "ILM",
			"partNumbers": [
				"G930F",
				"G930V"
			],
			"resourceCategory": "TROUBLESHOOTING"
		},
		{
			"id": "901a7f1e-a6f4-46fa-97ef-2ae45de10e77",
			"filename": "IF3290031_NA/EQ_IMAGE_REF/IF3290031.PNG",
			"label": null,
			"lastModified": "2020-08-05T07:43:40.468Z",
			"contentId": "EQ_IMAGE_REF",
			"language": "NA",
			"designation": "GALAXY S7 SPEAKER",
			"maintenanceLevel": "NA",
			"partNumbers": [
				"IF3290031"
			],
			"resourceCategory": "IMAGE"
		},
		{
			"id": "937afb5f-5509-49e2-ae5c-2aba1cedad0f",
			"filename": "A1984_EN/REPAIR_TUTO/repair_summary.json",
			"label": null,
			"lastModified": "2020-08-19T11:55:43.366Z",
			"contentId": "REPAIR_TUTO",
			"language": "en",
			"designation": "iPhone XR",
			"maintenanceLevel": "ILM",
			"partNumbers": [
				"A1984"
			],
			"resourceCategory": "REPAIR"
		},
		{
			"id": "93a8a4ed-a22e-4882-8ac4-673eb086ec9e",
			"filename": "A1984_EN/REPAIR_TUTO/Perform_an_unresponsive_reset.json",
			"label": null,
			"lastModified": "2020-08-19T11:55:43.368Z",
			"contentId": "REPAIR_TUTO",
			"language": "en",
			"designation": "iPhone XR",
			"maintenanceLevel": "ILM",
			"partNumbers": [
				"A1984"
			],
			"resourceCategory": "REPAIR"
		},
		{
			"id": "93c8addf-35c7-40c1-9939-cd4b7a7ce236",
			"filename": "S8/fr/ILM/G950F/REPAIR_TUTO/reparation-galaxy-s8-af960b42-2693-4624-bac5-32aa9c5fce38.json",
			"label": "reparation-galaxy-s8-af960b42-2693-4624-bac5-32aa9c5fce38.json",
			"lastModified": "2020-10-13T11:34:48.852Z",
			"contentId": "REPAIR_TUTO",
			"language": "fr",
			"designation": "S8",
			"maintenanceLevel": "ILM",
			"partNumbers": [
				"G950F"
			],
			"resourceCategory": "REPAIR"
		},
		{
			"id": "94c1537f-3c2f-4731-84a6-f712672c1077",
			"filename": "0123456789_FR/DOC_MAE/REPAIR_TUTO/resources/bleu-1.png",
			"label": null,
			"lastModified": "2020-06-24T11:41:00.350Z",
			"contentId": "DOC_MAE",
			"language": "fr",
			"designation": "TEST",
			"maintenanceLevel": "OLM",
			"partNumbers": [
				"0123456789"
			],
			"resourceCategory": "DOC"
		},
		{
			"id": "97e9e239-b599-46df-9ce2-5d6549061753",
			"filename": "IF3290071_NA/EQ_IMAGE_REF/IF3290071.PNG",
			"label": null,
			"lastModified": "2020-08-05T07:45:43.248Z",
			"contentId": "EQ_IMAGE_REF",
			"language": "NA",
			"designation": "GALAXY S7 CHARGING DAUGHTER BOARD (VERIZON)",
			"maintenanceLevel": "NA",
			"partNumbers": [
				"IF3290071"
			],
			"resourceCategory": "IMAGE"
		},
		{
			"id": "983b2eb4-1ce1-45ae-9be6-14fe71d070f3",
			"filename": "S7/fr/ILM/G930V/REPAIR_TUTO/resources/step12.png",
			"label": "step12.png",
			"lastModified": "2020-10-13T11:46:24.930Z",
			"contentId": "DIAG_EQ_TREE",
			"language": "fr",
			"designation": "S7",
			"maintenanceLevel": "ILM",
			"partNumbers": [
				"G930F",
				"G930V"
			],
			"resourceCategory": "TROUBLESHOOTING"
		},
		{
			"id": "9a1b0432-6815-4b2c-a332-b84ba975e2d8",
			"filename": "S7/fr/ILM/G930V/REPAIR_TUTO/resources/step8-3.png",
			"label": "step8-3.png",
			"lastModified": "2020-10-13T11:46:24.850Z",
			"contentId": "DIAG_EQ_TREE",
			"language": "fr",
			"designation": "S7",
			"maintenanceLevel": "ILM",
			"partNumbers": [
				"G930F",
				"G930V"
			],
			"resourceCategory": "TROUBLESHOOTING"
		},
		{
			"id": "9c16f3c9-e373-4e85-aa71-3335f9b72720",
			"filename": "A1984_EN/DIAG_EQ_TREE/troubleshooting-5f3d10ce0ecd1b00188ef0e5.json",
			"label": "iPhone XR - How to power on/off device",
			"lastModified": "2020-08-19T11:55:43.188Z",
			"contentId": "DIAG_EQ_TREE",
			"language": "en",
			"designation": "iPhone XR",
			"maintenanceLevel": "ILM",
			"partNumbers": [
				"A1984"
			],
			"resourceCategory": "TROUBLESHOOTING"
		},
		{
			"id": "a6363e5b-60fb-46c7-8e3e-caa97d9475e7",
			"filename": "S7/fr/ILM/G930V/DIAG_EQ_TREE/resources/maxresdefault.jpg",
			"label": "maxresdefault.jpg",
			"lastModified": "2020-10-13T11:46:24.633Z",
			"contentId": "DIAG_EQ_TREE",
			"language": "fr",
			"designation": "S7",
			"maintenanceLevel": "ILM",
			"partNumbers": [
				"G930F",
				"G930V"
			],
			"resourceCategory": "TROUBLESHOOTING"
		},
		{
			"id": "ab08b77c-0738-48b2-9bc6-fd5e6f7cccb7",
			"filename": "S7/fr/ILM/G930F/REPAIR_TUTO/repair_summary.json",
			"label": "",
			"lastModified": "2020-10-13T11:46:24.585Z",
			"contentId": "REPAIR_TUTO",
			"language": "fr",
			"designation": "S7",
			"maintenanceLevel": "ILM",
			"partNumbers": [
				"G930F",
				"G930V"
			],
			"resourceCategory": "REPAIR"
		},
		{
			"id": "ae138b22-dedf-400a-b922-605276199f6a",
			"filename": "S7/fr/ILM/G930F/REPAIR_TUTO/resources/step6.png",
			"label": "step6.png",
			"lastModified": "2020-10-13T11:46:24.275Z",
			"contentId": "DIAG_EQ_TREE",
			"language": "fr",
			"designation": "S7",
			"maintenanceLevel": "ILM",
			"partNumbers": [
				"G930F",
				"G930V"
			],
			"resourceCategory": "TROUBLESHOOTING"
		},
		{
			"id": "b0353a51-b359-4a2b-a932-f0356ba36d5e",
			"filename": "A1984_EN/REPAIR_TUTO/resources/XRstep1.jpg",
			"label": null,
			"lastModified": "2020-08-19T11:55:43.245Z",
			"contentId": "REPAIR_TUTO",
			"language": "en",
			"designation": "iPhone XR",
			"maintenanceLevel": "ILM",
			"partNumbers": [
				"A1984"
			],
			"resourceCategory": "REPAIR"
		},
		{
			"id": "b133e727-f202-4eab-9348-24a5f206134d",
			"filename": "S7/fr/ILM/G930V/REPAIR_TUTO/resources/step4.png",
			"label": "step4.png",
			"lastModified": "2020-10-13T11:46:24.719Z",
			"contentId": "DIAG_EQ_TREE",
			"language": "fr",
			"designation": "S7",
			"maintenanceLevel": "ILM",
			"partNumbers": [
				"G930F",
				"G930V"
			],
			"resourceCategory": "TROUBLESHOOTING"
		},
		{
			"id": "b329ed9f-0ba4-48b9-ae38-6afad79a4fa4",
			"filename": "S8/NA/EQ_IMAGE_REF/default.jpg",
			"label": "default.jpg",
			"lastModified": "2020-10-13T11:34:48.940Z",
			"contentId": "EQ_IMAGE_REF",
			"language": "fr",
			"designation": "S8",
			"maintenanceLevel": "ILM",
			"partNumbers": [
				"G950F"
			],
			"resourceCategory": "IMAGE"
		},
		{
			"id": "b4403600-0316-4cf8-bf24-9177262a0d73",
			"filename": "0123456789_FR/DOC_MAE/REPAIR_TUTO/resources/bleu-2.png",
			"label": null,
			"lastModified": "2020-06-24T11:41:00.351Z",
			"contentId": "DOC_MAE",
			"language": "fr",
			"designation": "TEST",
			"maintenanceLevel": "OLM",
			"partNumbers": [
				"0123456789"
			],
			"resourceCategory": "DOC"
		},
		{
			"id": "b60d5ccf-83b3-40bb-b8b0-b871cb6a90a0",
			"filename": "S8/fr/ILM/G950F/REPAIR_TUTO/resources/step1.png",
			"label": "step1.png",
			"lastModified": "2020-10-13T11:34:48.811Z",
			"contentId": "DIAG_EQ_TREE",
			"language": "fr",
			"designation": "S8",
			"maintenanceLevel": "ILM",
			"partNumbers": [
				"G950F"
			],
			"resourceCategory": "TROUBLESHOOTING"
		},
		{
			"id": "b950cb33-9c84-4fb2-b9d4-355afa80222d",
			"filename": "S7/fr/ILM/G930F/REPAIR_TUTO/resources/step10.png",
			"label": "step10.png",
			"lastModified": "2020-10-13T11:46:24.416Z",
			"contentId": "DIAG_EQ_TREE",
			"language": "fr",
			"designation": "S7",
			"maintenanceLevel": "ILM",
			"partNumbers": [
				"G930F",
				"G930V"
			],
			"resourceCategory": "TROUBLESHOOTING"
		},
		{
			"id": "bd105de9-8f48-454a-b391-74cb350bd7b4",
			"filename": "S7/fr/ILM/G930F/DIAG_EQ_TREE/troubleshooting-6378aff5-5d8d-41f8-a4b9-f781e5edf233.json",
			"label": "Samsung Galaxy S7 - Batterie",
			"lastModified": "2020-10-13T11:46:24.022Z",
			"contentId": "DIAG_EQ_TREE",
			"language": "fr",
			"designation": "S7",
			"maintenanceLevel": "ILM",
			"partNumbers": [
				"G930F",
				"G930V"
			],
			"resourceCategory": "TROUBLESHOOTING"
		},
		{
			"id": "be3534a9-262d-4c03-a358-9f74ed8fe7f7",
			"filename": "A1984_EN/REPAIR_TUTO/resources/XRstep4.jpg",
			"label": null,
			"lastModified": "2020-08-19T11:55:43.353Z",
			"contentId": "REPAIR_TUTO",
			"language": "en",
			"designation": "iPhone XR",
			"maintenanceLevel": "ILM",
			"partNumbers": [
				"A1984"
			],
			"resourceCategory": "REPAIR"
		},
		{
			"id": "bfe69e34-2533-4d9e-bfce-9b946c077fcf",
			"filename": "A1984_EN/EQ_IMAGE_REF/XRref.png",
			"label": null,
			"lastModified": "2020-08-19T11:55:43.438Z",
			"contentId": "EQ_IMAGE_REF",
			"language": "en",
			"designation": "iPhone XR",
			"maintenanceLevel": "ILM",
			"partNumbers": [
				"A1984"
			],
			"resourceCategory": "IMAGE"
		},
		{
			"id": "bfeae4e3-9778-4677-8f76-6806cb057245",
			"filename": "S7/fr/ILM/G930V/REPAIR_TUTO/resources/step11.png",
			"label": "step11.png",
			"lastModified": "2020-10-13T11:46:24.911Z",
			"contentId": "DIAG_EQ_TREE",
			"language": "fr",
			"designation": "S7",
			"maintenanceLevel": "ILM",
			"partNumbers": [
				"G930F",
				"G930V"
			],
			"resourceCategory": "TROUBLESHOOTING"
		},
		{
			"id": "c1c5034a-e7e5-4db3-8c1b-b051f493baea",
			"filename": "S7/fr/ILM/G930F/DIAG_EQ_TREE/resources/maxresdefault.jpg",
			"label": "maxresdefault.jpg",
			"lastModified": "2020-10-13T11:46:24.093Z",
			"contentId": "DIAG_EQ_TREE",
			"language": "fr",
			"designation": "S7",
			"maintenanceLevel": "ILM",
			"partNumbers": [
				"G930F",
				"G930V"
			],
			"resourceCategory": "TROUBLESHOOTING"
		},
		{
			"id": "c7888104-482e-49e7-af5e-5509f4739614",
			"filename": "A1984_EN/REPAIR_TUTO/resources/XRstep3.jpg",
			"label": null,
			"lastModified": "2020-08-19T11:55:43.272Z",
			"contentId": "REPAIR_TUTO",
			"language": "en",
			"designation": "iPhone XR",
			"maintenanceLevel": "ILM",
			"partNumbers": [
				"A1984"
			],
			"resourceCategory": "REPAIR"
		},
		{
			"id": "cd367d21-9b68-4e8e-8fa2-b07b497b7c62",
			"filename": "S7/fr/ILM/G930F/REPAIR_TUTO/resources/step7.png",
			"label": "step7.png",
			"lastModified": "2020-10-13T11:46:24.304Z",
			"contentId": "DIAG_EQ_TREE",
			"language": "fr",
			"designation": "S7",
			"maintenanceLevel": "ILM",
			"partNumbers": [
				"G930F",
				"G930V"
			],
			"resourceCategory": "TROUBLESHOOTING"
		},
		{
			"id": "cd4b712d-928b-44bc-8ed8-ca5c69ff464b",
			"filename": "S7/fr/ILM/G930F/REPAIR_TUTO/resources/step8-3.png",
			"label": "step8-3.png",
			"lastModified": "2020-10-13T11:46:24.371Z",
			"contentId": "DIAG_EQ_TREE",
			"language": "fr",
			"designation": "S7",
			"maintenanceLevel": "ILM",
			"partNumbers": [
				"G930F",
				"G930V"
			],
			"resourceCategory": "TROUBLESHOOTING"
		},
		{
			"id": "cfb1652a-0a61-455b-9a7f-c124061f0709",
			"filename": "S7/fr/ILM/G930V/REPAIR_TUTO/resources/step7.png",
			"label": "step7.png",
			"lastModified": "2020-10-13T11:46:24.793Z",
			"contentId": "DIAG_EQ_TREE",
			"language": "fr",
			"designation": "S7",
			"maintenanceLevel": "ILM",
			"partNumbers": [
				"G930F",
				"G930V"
			],
			"resourceCategory": "TROUBLESHOOTING"
		},
		{
			"id": "d0cbce79-028f-4ffb-b415-7ba98bc3c5c5",
			"filename": "S7/fr/ILM/G930F/REPAIR_TUTO/resources/step4.png",
			"label": "step4.png",
			"lastModified": "2020-10-13T11:46:24.225Z",
			"contentId": "DIAG_EQ_TREE",
			"language": "fr",
			"designation": "S7",
			"maintenanceLevel": "ILM",
			"partNumbers": [
				"G930F",
				"G930V"
			],
			"resourceCategory": "TROUBLESHOOTING"
		},
		{
			"id": "d125a5e4-112d-4c92-a47a-301f7aa0c935",
			"filename": "S7/fr/ILM/G930F/REPAIR_TUTO/resources/step11.png",
			"label": "step11.png",
			"lastModified": "2020-10-13T11:46:24.460Z",
			"contentId": "DIAG_EQ_TREE",
			"language": "fr",
			"designation": "S7",
			"maintenanceLevel": "ILM",
			"partNumbers": [
				"G930F",
				"G930V"
			],
			"resourceCategory": "TROUBLESHOOTING"
		},
		{
			"id": "d8aa0c6a-2548-4e61-a296-19f6e59d2aab",
			"filename": "S7/fr/ILM/G930F/REPAIR_TUTO/resources/step14-2.png",
			"label": "step14-2.png",
			"lastModified": "2020-10-13T11:46:24.548Z",
			"contentId": "DIAG_EQ_TREE",
			"language": "fr",
			"designation": "S7",
			"maintenanceLevel": "ILM",
			"partNumbers": [
				"G930F",
				"G930V"
			],
			"resourceCategory": "TROUBLESHOOTING"
		},
		{
			"id": "db52e6b5-428b-43fc-bd81-9c0ec5c4e05f",
			"filename": "S7/fr/ILM/G930V/REPAIR_TUTO/resources/step9.png",
			"label": "step9.png",
			"lastModified": "2020-10-13T11:46:24.870Z",
			"contentId": "DIAG_EQ_TREE",
			"language": "fr",
			"designation": "S7",
			"maintenanceLevel": "ILM",
			"partNumbers": [
				"G930F",
				"G930V"
			],
			"resourceCategory": "TROUBLESHOOTING"
		},
		{
			"id": "df1963ea-5c0d-461c-a3e0-7308b6d3d39c",
			"filename": "S7/fr/ILM/G930F/REPAIR_TUTO/resources/step8-1.png",
			"label": "step8-1.png",
			"lastModified": "2020-10-13T11:46:24.328Z",
			"contentId": "DIAG_EQ_TREE",
			"language": "fr",
			"designation": "S7",
			"maintenanceLevel": "ILM",
			"partNumbers": [
				"G930F",
				"G930V"
			],
			"resourceCategory": "TROUBLESHOOTING"
		},
		{
			"id": "df8173b2-9398-4c4a-aff0-cb18d130b376",
			"filename": "S7/fr/ILM/G930F/REPAIR_TUTO/resources/step12.png",
			"label": "step12.png",
			"lastModified": "2020-10-13T11:46:24.481Z",
			"contentId": "DIAG_EQ_TREE",
			"language": "fr",
			"designation": "S7",
			"maintenanceLevel": "ILM",
			"partNumbers": [
				"G930F",
				"G930V"
			],
			"resourceCategory": "TROUBLESHOOTING"
		},
		{
			"id": "e32f030e-6af0-4cdf-9b45-8518b25524a1",
			"filename": "IF3290101_NA/EQ_IMAGE_REF/IF3290101.PNG",
			"label": null,
			"lastModified": "2020-08-05T07:42:51.833Z",
			"contentId": "EQ_IMAGE_REF",
			"language": "NA",
			"designation": "GALAXY S7 HOME BUTTON AND CABLE ASSEMBLY",
			"maintenanceLevel": "NA",
			"partNumbers": [
				"IF3290101"
			],
			"resourceCategory": "IMAGE"
		},
		{
			"id": "e3610859-4572-42ba-bf47-5dfd466df0ca",
			"filename": "S7/fr/ILM/G930V/REPAIR_TUTO/resources/step14-2.png",
			"label": "step14-2.png",
			"lastModified": "2020-10-13T11:46:25.008Z",
			"contentId": "DIAG_EQ_TREE",
			"language": "fr",
			"designation": "S7",
			"maintenanceLevel": "ILM",
			"partNumbers": [
				"G930F",
				"G930V"
			],
			"resourceCategory": "TROUBLESHOOTING"
		},
		{
			"id": "e78c1482-a5cf-4089-b269-451488dfee0e",
			"filename": "S8/fr/ILM/G950F/DIAG_EQ_TREE/resources/maxresdefault.jpg",
			"label": "maxresdefault.jpg",
			"lastModified": "2020-10-13T11:34:48.786Z",
			"contentId": "DIAG_EQ_TREE",
			"language": "fr",
			"designation": "S8",
			"maintenanceLevel": "ILM",
			"partNumbers": [
				"G950F"
			],
			"resourceCategory": "TROUBLESHOOTING"
		},
		{
			"id": "e8008915-0692-4d67-b79d-f10acc587b72",
			"filename": "S7/fr/ILM/G930F/REPAIR_TUTO/resources/step3.png",
			"label": "step3.png",
			"lastModified": "2020-10-13T11:46:24.201Z",
			"contentId": "DIAG_EQ_TREE",
			"language": "fr",
			"designation": "S7",
			"maintenanceLevel": "ILM",
			"partNumbers": [
				"G930F",
				"G930V"
			],
			"resourceCategory": "TROUBLESHOOTING"
		},
		{
			"id": "f0623ff6-b1ea-4cdc-b58d-89e02b3bc068",
			"filename": "S8/fr/ILM/G950F/REPAIR_TUTO/repair_summary.json",
			"label": "",
			"lastModified": "2020-10-13T11:34:48.875Z",
			"contentId": "REPAIR_TUTO",
			"language": "fr",
			"designation": "S8",
			"maintenanceLevel": "ILM",
			"partNumbers": [
				"G950F"
			],
			"resourceCategory": "REPAIR"
		},
		{
			"id": "f12bad52-4dfc-4e21-971f-aa1760b1e5a6",
			"filename": "A1984_EN/REPAIR_TUTO/resources/XRstep2.jpg",
			"label": null,
			"lastModified": "2020-08-19T11:55:43.276Z",
			"contentId": "REPAIR_TUTO",
			"language": "en",
			"designation": "iPhone XR",
			"maintenanceLevel": "ILM",
			"partNumbers": [
				"A1984"
			],
			"resourceCategory": "REPAIR"
		},
		{
			"id": "f5f2e49b-cc7e-4fc8-8418-010a2a383d04",
			"filename": "A2111_FR/REPAIR_TUTO/resources/step1.jpg",
			"label": null,
			"lastModified": "2020-08-18T11:21:49.424Z",
			"contentId": "REPAIR_TUTO",
			"language": "fr",
			"designation": "iPhone 11",
			"maintenanceLevel": "ILM",
			"partNumbers": [
				"A2111"
			],
			"resourceCategory": "REPAIR"
		},
		{
			"id": "f699e489-434d-4f35-810d-06a9ad097688",
			"filename": "0123456789_FR/DOC_MTMI/example.pdf",
			"label": null,
			"lastModified": "2020-06-24T10:19:29.820Z",
			"contentId": "DOC_MTMI",
			"language": "fr",
			"designation": "TEST",
			"maintenanceLevel": "OLM",
			"partNumbers": [
				"0123456789"
			],
			"resourceCategory": "DOC"
		},
		{
			"id": "fc14ad70-c2b6-4f62-82ee-d31933a2db9d",
			"filename": "S7/fr/ILM/G930V/REPAIR_TUTO/resources/step2.png",
			"label": "step2.png",
			"lastModified": "2020-10-13T11:46:24.679Z",
			"contentId": "DIAG_EQ_TREE",
			"language": "fr",
			"designation": "S7",
			"maintenanceLevel": "ILM",
			"partNumbers": [
				"G930F",
				"G930V"
			],
			"resourceCategory": "TROUBLESHOOTING"
		},
		{
			"id": "fefb8c2a-4ae8-4a3b-9909-5c37481f79b5",
			"filename": "S8/fr/ILM/DOC_MAE/example.pdf",
			"label": "example.pdf",
			"lastModified": "2020-10-13T11:34:48.913Z",
			"contentId": "DOC_MAE",
			"language": "fr",
			"designation": "S8",
			"maintenanceLevel": "ILM",
			"partNumbers": [
				"G950F"
			],
			"resourceCategory": "DOC"
		}
	]
}
